lcaplatform_config/__init__.py
lcaplatform_config/config.py
lcaplatform_config/connection.py
lcaplatform_config/context.py
lcaplatform_config/email.py
lcaplatform_config/exceptions.py
lcaplatform_config/fastapi.py
lcaplatform_config/formatting.py
lcaplatform_config/graphql/__init__.py
lcaplatform_config/graphql/input_filters.py
lcaplatform_config/graphql/pagination.py
lcaplatform_config/load_db.py
lcaplatform_config/logging.conf
lcaplatform_config/logging.py
lcaplatform_config/logging_traces.conf
lcaplatform_config/monitoring.py
lcaplatform_config/permissions.py
lcaplatform_config/router.py
lcaplatform_config/security.py
lcaplatform_config/user.py
lcaplatform_config/validate.py
lcaplatform_config-0.4.2.dist-info/METADATA
lcaplatform_config-0.4.2.dist-info/WHEEL
lcaplatform_config-0.4.2.dist-info/licenses/LICENSE
lcaplatform_config-0.4.2.dist-info/RECORD
